Metadata-Version: 1.0
Name: slashify
Version: 1.0.1
Summary: Automatically convert discord.py commands to slash commands!
Home-page: https://github.com/tag-epic/slashify
Author: Epic
Author-email: tagepicuwu@gmail.com
License: UNKNOWN
Platform: UNKNOWN
